<?xml version="1.0" encoding="UTF-8" ?>
<result>
	<isbn>0140440852</isbn>
	<tag>3rd century bc</tag>
	<occurrences>/tag/3rd+century+bc" target="_top">3rd century bc</a><span class="count"> (10</occurrences>
	<user/>
	<review/>
	<isbn>0140440852</isbn>
	<tag>ancient</tag>
	<occurrences>/tag/ancient" target="_top">ancient</a><span class="count"> (13</occurrences>
	<user/>
	<review/>
	<isbn>0140440852</isbn>
	<tag>ancient greece</tag>
	<occurrences>/tag/ancient+greece" target="_top">ancient greece</a><span class="count"> (20</occurrences>
	<user/>
	<review/>
	<isbn>0140440852</isbn>
	<tag>ancient greek</tag>
	<occurrences>/tag/ancient+greek" target="_top">ancient greek</a><span class="count"> (11</occurrences>
	<user/>
	<review/>
	<isbn>0140440852</isbn>
	<tag>ancient greek literature</tag>
	<occurrences>/tag/ancient+greek+literature" target="_top">ancient greek literature</a></b><span class="count"> (9</occurrences>
	<user/>
	<review/>
	<isbn>0140440852</isbn>
	<tag>ancient literature</tag>
	<occurrences>/tag/ancient+literature" target="_top">ancient literature</a></b><span class="count"> (12</occurrences>
	<user/>
	<review/>
	<isbn>0140440852</isbn>
	<tag>antiquity</tag>
	<occurrences>/tag/antiquity" target="_top">antiquity</a><span class="count"> (9</occurrences>
	<user/>
	<review/>
	<isbn>0140440852</isbn>
	<tag>apollonius rhodius</tag>
	<occurrences>/tag/apollonius+rhodius" target="_top">apollonius rhodius</a><span class="count"> (15</occurrences>
	<user/>
	<review/>
	<isbn>0140440852</isbn>
	<tag>classic</tag>
	<occurrences>/tag/classic" target="_top">classic</a><span class="count"> (23</occurrences>
	<user/>
	<review/>
	<isbn>0140440852</isbn>
	<tag>classical</tag>
	<occurrences>/tag/classical" target="_top">classical</a><span class="count"> (18</occurrences>
	<user/>
	<review/>
	<isbn>0140440852</isbn>
	<tag>classical literature</tag>
	<occurrences>/tag/classical+literature" target="_top">classical literature</a><span class="count"> (19</occurrences>
	<user/>
	<review/>
	<isbn>0140440852</isbn>
	<tag>classical studies</tag>
	<occurrences>/tag/classical+studies" target="_top">classical studies</a><span class="count"> (9</occurrences>
	<user/>
	<review/>
	<isbn>0140440852</isbn>
	<tag>classics</tag>
	<occurrences>/tag/classics" target="_top">classics</a><span class="count"> (94</occurrences>
	<user/>
	<review/>
	<isbn>0140440852</isbn>
	<tag>epic</tag>
	<occurrences>/tag/epic" target="_top">epic</a><span class="count"> (40</occurrences>
	<user/>
	<review/>
	<isbn>0140440852</isbn>
	<tag>epic poetry</tag>
	<occurrences>/tag/epic+poetry" target="_top">epic poetry</a></b><span class="count"> (19</occurrences>
	<user/>
	<review/>
	<isbn>0140440852</isbn>
	<tag>fiction</tag>
	<occurrences>/tag/fiction" target="_top">fiction</a><span class="count"> (44</occurrences>
	<user/>
	<review/>
	<isbn>0140440852</isbn>
	<tag>greece</tag>
	<occurrences>/tag/greece" target="_top">greece</a><span class="count"> (31</occurrences>
	<user/>
	<review/>
	<isbn>0140440852</isbn>
	<tag>greek</tag>
	<occurrences>/tag/greek" target="_top">greek</a></b><span class="count"> (71</occurrences>
	<user/>
	<review/>
	<isbn>0140440852</isbn>
	<tag>greek literature</tag>
	<occurrences>/tag/greek+literature" target="_top">greek literature</a></b><span class="count"> (45</occurrences>
	<user/>
	<review/>
	<isbn>0140440852</isbn>
	<tag>greek mythology</tag>
	<occurrences>/tag/greek+mythology" target="_top">greek mythology</a></b><span class="count"> (20</occurrences>
	<user/>
	<review/>
	<isbn>0140440852</isbn>
	<tag>greek poetry</tag>
	<occurrences>/tag/greek+poetry" target="_top">greek poetry</a></b><span class="count"> (12</occurrences>
	<user/>
	<review/>
	<isbn>0140440852</isbn>
	<tag>history</tag>
	<occurrences>/tag/history" target="_top">history</a><span class="count"> (11</occurrences>
	<user/>
	<review/>
	<isbn>0140440852</isbn>
	<tag>jason</tag>
	<occurrences>/tag/jason" target="_top">jason</a></b><span class="count"> (8</occurrences>
	<user/>
	<review/>
	<isbn>0140440852</isbn>
	<tag>literature</tag>
	<occurrences>/tag/literature" target="_top">literature</a><span class="count"> (40</occurrences>
	<user/>
	<review/>
	<isbn>0140440852</isbn>
	<tag>loeb</tag>
	<occurrences>/tag/loeb" target="_top">loeb</a></b><span class="count"> (16</occurrences>
	<user/>
	<review/>
	<isbn>0140440852</isbn>
	<tag>myth</tag>
	<occurrences>/tag/myth" target="_top">myth</a><span class="count"> (14</occurrences>
	<user/>
	<review/>
	<isbn>0140440852</isbn>
	<tag>mythology</tag>
	<occurrences>/tag/mythology" target="_top">mythology</a></b><span class="count"> (100</occurrences>
	<user/>
	<review/>
	<isbn>0140440852</isbn>
	<tag>penguin classics</tag>
	<occurrences>/tag/penguin+classics" target="_top">penguin classics</a><span class="count"> (17</occurrences>
	<user/>
	<review/>
	<isbn>0140440852</isbn>
	<tag>poetry</tag>
	<occurrences>/tag/poetry" target="_top">poetry</a><span class="count"> (67</occurrences>
	<user/>
	<review/>
	<isbn>0140440852</isbn>
	<tag>translation</tag>
	<occurrences>/tag/translation" target="_top">translation</a><span class="count"> (27</occurrences>
	<user/>
	<review/>
</result>