<?xml version="1.0" encoding="UTF-8" ?>
<result>
	<isbn>1578563682</isbn>
	<tag>christianity</tag>
	<occurrences>27</occurrences>
	<user/>
	<review/>
	<isbn>1578563682</isbn>
	<tag>men</tag>
	<occurrences>14</occurrences>
	<user/>
	<review/>
	<isbn>1578563682</isbn>
	<tag>sex</tag>
	<occurrences>14</occurrences>
	<user/>
	<review/>
	<isbn>1578563682</isbn>
	<tag>purity</tag>
	<occurrences>11</occurrences>
	<user/>
	<review/>
	<isbn>1578563682</isbn>
	<tag>lust</tag>
	<occurrences>9</occurrences>
	<user/>
	<review/>
	<isbn>1578563682</isbn>
	<tag>marriage</tag>
	<occurrences>7</occurrences>
	<user/>
	<review/>
	<isbn>1578563682</isbn>
	<tag>book</tag>
	<occurrences>3</occurrences>
	<user/>
	<review/>
	<isbn>1578563682</isbn>
	<tag>counseling</tag>
	<occurrences>3</occurrences>
	<user/>
	<review/>
	<isbn>1578563682</isbn>
	<tag>anger management</tag>
	<occurrences>2</occurrences>
	<user/>
	<review/>
	<isbn>1578563682</isbn>
	<tag>catholic</tag>
	<occurrences>2</occurrences>
	<user/>
	<review/>
	<isbn>1578563682</isbn>
	<tag>christian sexuality maleness</tag>
	<occurrences>1</occurrences>
	<user/>
	<review/>
	<isbn>1578563682</isbn>
	<tag>eric smith</tag>
	<occurrences>1</occurrences>
	<user/>
	<review/>
	<isbn>1578563682</isbn>
	<tag>freedom from sin</tag>
	<occurrences>1</occurrences>
	<user/>
	<review/>
	<isbn>1578563682</isbn>
	<tag>goddess</tag>
	<occurrences>1</occurrences>
	<user/>
	<review/>
	<isbn>1578563682</isbn>
	<tag>mens health</tag>
	<occurrences>1</occurrences>
	<user/>
	<review/>
	<isbn>1578563682</isbn>
	<tag>myth</tag>
	<occurrences>1</occurrences>
	<user/>
	<review/>
	<isbn>1578563682</isbn>
	<tag>overcoming lust</tag>
	<occurrences>1</occurrences>
	<user/>
	<review/>
	<isbn>1578563682</isbn>
	<tag>porn addiction</tag>
	<occurrences>1</occurrences>
	<user/>
	<review/>
	<isbn>1578563682</isbn>
	<tag>self help book</tag>
	<occurrences>1</occurrences>
	<user/>
	<review/>
	<isbn>1578563682</isbn>
	<tag>sex addict</tag>
	<occurrences>1</occurrences>
	<user/>
	<review/>
	<isbn>1578563682</isbn>
	<tag>sex addiction</tag>
	<occurrences>1</occurrences>
	<user/>
	<review/>
	<isbn>1578563682</isbn>
	<tag>sexual addiction</tag>
	<occurrences>1</occurrences>
	<user/>
	<review/>
	<isbn>1578563682</isbn>
	<tag>sexual integrity</tag>
	<occurrences>1</occurrences>
	<user/>
	<review/>
	<isbn>1578563682</isbn>
	<tag>sexual purity</tag>
	<occurrences>1</occurrences>
	<user/>
	<review/>
	<isbn>1578563682</isbn>
	<tag>sexual temptation</tag>
	<occurrences>1</occurrences>
	<user/>
	<review/>
	<isbn>1578563682</isbn>
	<tag>sexuality</tag>
	<occurrences>1</occurrences>
	<user/>
	<review/>
	<isbn>1578563682</isbn>
	<tag>sin</tag>
	<occurrences>1</occurrences>
	<user/>
	<review/>
	<isbn>1578563682</isbn>
	<tag>spirituality</tag>
	<occurrences>1</occurrences>
	<user/>
	<review/>
	<isbn>1578563682</isbn>
	<tag>theocracy</tag>
	<occurrences>1</occurrences>
	<user/>
	<review/>
	<isbn>1578563682</isbn>
	<tag>watchman nee</tag>
	<occurrences>1</occurrences>
	<user/>
	<review/>
	<isbn>1578563682</isbn>
	<tag>women</tag>
	<occurrences>1</occurrences>
	<user/>
	<review/>
</result>